[
    {
        "place": "1",
        "equipe": "HOLTZHEIM VOGESIA",
        "pts_equipe": "10",
        "nb_match": "5",
        "victoire": "5",
        "defaite": "0",
        "pts_marques": "273",
        "pts_encaisses": "189",
        "difference": "84"
    },
    {
        "place": "2",
        "equipe": "GEISPOLSHEIM C.J.S.",
        "pts_equipe": "8",
        "nb_match": "5",
        "victoire": "3",
        "defaite": "2",
        "pts_marques": "265",
        "pts_encaisses": "208",
        "difference": "57"
    },
    {
        "place": "3",
        "equipe": "ECKBOLSHEIM BB",
        "pts_equipe": "7",
        "nb_match": "4",
        "victoire": "3",
        "defaite": "1",
        "pts_marques": "187",
        "pts_encaisses": "177",
        "difference": "10"
    },
    {
        "place": "4",
        "equipe": "HAMBACH BC",
        "pts_equipe": "6",
        "nb_match": "4",
        "victoire": "2",
        "defaite": "2",
        "pts_marques": "167",
        "pts_encaisses": "177",
        "difference": "-10"
    },
    {
        "place": "5",
        "equipe": "STRASBOURG SAINT JOSEPH",
        "pts_equipe": "6",
        "nb_match": "5",
        "victoire": "1",
        "defaite": "4",
        "pts_marques": "226",
        "pts_encaisses": "263",
        "difference": "-37"
    },
    {
        "place": "6",
        "equipe": "BRUCHE SPORTS ACADEMY",
        "pts_equipe": "5",
        "nb_match": "5",
        "victoire": "0",
        "defaite": "5",
        "pts_marques": "193",
        "pts_encaisses": "297",
        "difference": "-104"
    }
]